ames/__init__.py
ames/utils.py
ames/converters/__init__.py
ames/converters/codemeta_to_datacite.py
ames/converters/epfmt.py
ames/exec/Linux/epfmt
ames/exec/Linux/eputil
ames/exec/MacOS/epfmt
ames/exec/MacOS/eputil
ames/exec/Win/epfmt.exe
ames/exec/Win/eputil.exe
ames/harvesters/__init__.py
ames/harvesters/caltechauthors.py
ames/harvesters/caltechdata.py
ames/harvesters/caltechfeeds.py
ames/harvesters/crossref_refs.py
ames/harvesters/datacite.py
ames/harvesters/eprints_extended.py
ames/harvesters/eputil.py
ames/harvesters/github.py
ames/harvesters/orcid.py
ames/harvesters/usage.py
ames/matchers/__init__.py
ames/matchers/caltechauthors.py
ames/matchers/caltechdata.py
ames/matchers/datacite.py
ames/matchers/eprints.py
ames-1.2.2.dist-info/LICENSE
ames-1.2.2.dist-info/METADATA
ames-1.2.2.dist-info/WHEEL
ames-1.2.2.dist-info/top_level.txt
ames-1.2.2.dist-info/RECORD
