Metadata-Version: 2.1
Name: ames
Version: 1.2.2
Summary: Automated Metadata Service: Manage metadata from different sources.
Home-page: https://github.com/caltechlibrary/ames
Author: Thomas E Morrell, Robert Doiel, Rohan Bhattarai, Elizabeth Won, Alexander Abakah
Author-email: tmorrell@caltech.edu, rsdoiel@caltech.edu, rbhattar@caltech.edu
License: https://data.caltech.edu/license
Platform: UNKNOWN
Classifier: License :: OSI Approved :: BSD License
Classifier: Programming Language :: Python
Classifier: Programming Language :: Python :: 3
Classifier: Programming Language :: Python :: 3.7
Classifier: Programming Language :: Python :: Implementation :: CPython
Classifier: Programming Language :: Python :: Implementation :: PyPy
Requires-Python: >=3.7.0
License-File: LICENSE
Requires-Dist: requests
Requires-Dist: idutils
Requires-Dist: progressbar2
Requires-Dist: caltechdata-api>=1.0.0
Requires-Dist: py-dataset==1.0.1
Requires-Dist: pandas
Requires-Dist: ArchivesSnake
Requires-Dist: dimcli
